panpipelines/Factory.py
panpipelines/__init__.py
panpipelines/group_subjects.py
panpipelines/pan_processing.py
panpipelines/single_subject.py
panpipelines/version.py
panpipelines/nodes/__init__.py
panpipelines/nodes/antstransform.py
panpipelines/nodes/aslprep.py
panpipelines/nodes/atlascreate.py
panpipelines/nodes/basil.py
panpipelines/nodes/collate_csv_group.py
panpipelines/nodes/collate_csv_single.py
panpipelines/nodes/dummy.py
panpipelines/nodes/fmriprep.py
panpipelines/nodes/freesurfer.py
panpipelines/nodes/freesurferextra.py
panpipelines/nodes/freewater.py
panpipelines/nodes/fslanat.py
panpipelines/nodes/getbids.py
panpipelines/nodes/glm_randomize_group.py
panpipelines/nodes/lst.py
panpipelines/nodes/mriqc.py
panpipelines/nodes/mriqcgroup.py
panpipelines/nodes/noddi.py
panpipelines/nodes/pancontainergroup.py
panpipelines/nodes/parse_textdata.py
panpipelines/nodes/postxcpd.py
panpipelines/nodes/preproc.py
panpipelines/nodes/qsiprep.py
panpipelines/nodes/qsirecon.py
panpipelines/nodes/registration.py
panpipelines/nodes/reports.py
panpipelines/nodes/roi_extract.py
panpipelines/nodes/roi_mean_group.py
panpipelines/nodes/roi_mean_single.py
panpipelines/nodes/tensor.py
panpipelines/nodes/tractseg.py
panpipelines/nodes/tracula.py
panpipelines/nodes/upload.py
panpipelines/nodes/xcpd.py
panpipelines/nodes/xtract.py
panpipelines/pipelines/__init__.py
panpipelines/pipelines/aslprep_panpipeline.py
panpipelines/pipelines/basil_panpipeline.py
panpipelines/pipelines/collatecsv_panpipeline.py
panpipelines/pipelines/collatecsvgroup_panpipeline.py
panpipelines/pipelines/dummy_panpipeline.py
panpipelines/pipelines/fmriprep_panpipeline.py
panpipelines/pipelines/freesurfer_panpipeline.py
panpipelines/pipelines/getbids_panpipeline.py
panpipelines/pipelines/lst_panpipeline.py
panpipelines/pipelines/mriqc_panpipeline.py
panpipelines/pipelines/mriqcgroup_panpipeline.py
panpipelines/pipelines/noddi_panpipeline.py
panpipelines/pipelines/pancontainergroup_panpipeline.py
panpipelines-1.1.5.dist-info/METADATA
panpipelines-1.1.5.dist-info/WHEEL
panpipelines-1.1.5.dist-info/licenses/LICENSE
panpipelines-1.1.5.dist-info/RECORD
