Metadata-Version: 2.4
Name: panpipelines
Version: 1.1.5
Summary: MRI Processing Pipelines for PAN Healthy Minds for Life Study
Project-URL: Homepage, https://github.com/MRIresearch/PANpipelines
Project-URL: Bug Tracker, https://github.com/MRIresearch/PANpipelines/issues
Author-email: Chidi Ugonna <chidiugonna@arizona.edu>
License: MIT License
License-File: LICENSE
Classifier: License :: OSI Approved :: MIT License
Classifier: Operating System :: OS Independent
Classifier: Programming Language :: Python :: 3
Requires-Python: >=3.9
Requires-Dist: beautifulsoup4==4.12.3
Requires-Dist: dipy==1.10.0
Requires-Dist: dominate==2.9.1
Requires-Dist: mne[hdf]==1.1.0
Requires-Dist: nibabel==5.2.0
Requires-Dist: nilearn==0.10.2
Requires-Dist: nipype==1.8.6
Requires-Dist: nitransforms==23.0.1
Requires-Dist: numpy==1.26.3
Requires-Dist: pandas==2.1.4
Requires-Dist: paramiko==3.5.1
Requires-Dist: psycopg2-binary==2.9.10
Requires-Dist: pybids==0.16.4
Requires-Dist: pydicom==2.4.4
Requires-Dist: pysftp==0.2.9
Requires-Dist: scipy==1.11.4
Requires-Dist: sdcflows==2.8.0
Requires-Dist: sqlalchemy==2.0.34
Requires-Dist: templateflow==23.1.0
Requires-Dist: xnat==0.5.3
